flask_tryton.py
flask_tryton-0.12.2.dist-info/LICENSE
flask_tryton-0.12.2.dist-info/METADATA
flask_tryton-0.12.2.dist-info/WHEEL
flask_tryton-0.12.2.dist-info/top_level.txt
flask_tryton-0.12.2.dist-info/RECORD
