Metadata-Version: 2.2
Name: flask_tryton
Version: 0.12.2
Summary: Adds Tryton support to Flask application
Home-page: https://pypi.org/project/flask-tryton/
Download-URL: https://downloads.tryton.org/flask-tryton/
Author: Tryton
Author-email: foundation@tryton.org
License: GPL-3
Project-URL: Bug Tracker, https://bugs.tryton.org/flask-tryton
Project-URL: Forum, https://discuss.tryton.org/tags/flask
Project-URL: Source Code, https://code.tryton.org/flask-tryton
Keywords: flask tryton web
Platform: any
Classifier: Environment :: Web Environment
Classifier: Framework :: Tryton
Classifier: Framework :: Flask
Classifier: Intended Audience :: Developers
Classifier: License :: OSI Approved :: GNU General Public License (GPL)
Classifier: Operating System :: OS Independent
Classifier: Programming Language :: Python :: 3
Classifier: Topic :: Internet :: WWW/HTTP :: Dynamic Content
Classifier: Topic :: Software Development :: Libraries :: Python Modules
Requires-Python: >=3.6
License-File: LICENSE
Requires-Dist: Flask>=0.8
Requires-Dist: Werkzeug
Requires-Dist: trytond>=6.0
Dynamic: author
Dynamic: author-email
Dynamic: classifier
Dynamic: description
Dynamic: download-url
Dynamic: home-page
Dynamic: keywords
Dynamic: license
Dynamic: platform
Dynamic: project-url
Dynamic: requires-dist
Dynamic: requires-python
Dynamic: summary
